Locker.v
module digital_locker (
    input clk,
    input reset,
    input submit,
    input [3:0] digit_in,
    output reg unlocked,
    output reg locked,
    output reg [1:0] attempts_left
);

    // State encoding using parameter
    parameter IDLE = 2'b00, COMPARE = 2'b01, UNLOCKED_STATE = 2'b10, LOCKED_STATE = 2'b11;
    reg [1:0] current_state, next_state;

    // Password storage
    reg [3:0] password [3:0];
    initial begin
        password[0] = 4'd1;
        password[1] = 4'd2;
        password[2] = 4'd3;
        password[3] = 4'd4;
    end

    // Digit entry buffer
    reg [1:0] digit_index;  // 2-bit is fine: values 0 to 3
    reg [3:0] input_digits [3:0];
    reg match_flag;

    // FSM and input capture
    always @(posedge clk or posedge reset) begin
        if (reset) begin
            current_state <= IDLE;
            digit_index <= 0;
            attempts_left <= 2'd3;
            unlocked <= 0;
            locked <= 0;
        end else begin
            current_state <= next_state;

            // Capture digit on submit
            if (submit && current_state == IDLE) begin
                input_digits[digit_index] <= digit_in;

                if (digit_index == 2'd3)
                    next_state <= COMPARE;

                digit_index <= digit_index + 1;
            end
        end
    end

    // Next state logic and result check
    always @(*) begin
        next_state = current_state;
        match_flag = (
            input_digits[0] == password[0] &&
            input_digits[1] == password[1] &&
            input_digits[2] == password[2] &&
            input_digits[3] == password[3]
        );

        case (current_state)
            IDLE: begin
                unlocked = 0;
                locked = 0;
            end

            COMPARE: begin
                if (match_flag)
                    next_state = UNLOCKED_STATE;
                else if (attempts_left == 2'd1)
                    next_state = LOCKED_STATE;
                else
                    next_state = IDLE;
            end

            UNLOCKED_STATE: begin
                unlocked = 1;
            end

            LOCKED_STATE: begin
                locked = 1;
            end
        endcase
    end

    // Attempts and digit reset logic
    always @(posedge clk or posedge reset) begin
        if (reset) begin
            attempts_left <= 2'd3;
        end else if (current_state == COMPARE && !match_flag) begin
            attempts_left <= attempts_left - 1;
            digit_index <= 0;
        end
    end

endmodule

Locker_TB.v
`timescale 1ns / 1ps

module digital_locker_tb;

    reg clk, reset, submit;
    reg [3:0] digit_in;
    wire unlocked, locked;
    wire [1:0] attempts_left;

    digital_locker uut (
        .clk(clk), .reset(reset), .submit(submit), .digit_in(digit_in),
        .unlocked(unlocked), .locked(locked), .attempts_left(attempts_left)
    );

    initial clk = 0;
    always #5 clk = ~clk;

    task enter_code(input [3:0] d0, d1, d2, d3);
    begin
        digit_in = d0; submit = 1; #10; submit = 0; #10;
        digit_in = d1; submit = 1; #10; submit = 0; #10;
        digit_in = d2; submit = 1; #10; submit = 0; #10;
        digit_in = d3; submit = 1; #10; submit = 0; #10;
    end
    endtask

    initial begin
        $dumpfile("locker.vcd");
        $dumpvars(0, digital_locker_tb);

        reset = 1; submit = 0; digit_in = 0; #20;
        reset = 0; #10;

        // Correct password
        enter_code(4'd1, 4'd2, 4'd3, 4'd4);
        #50;

        // Reset to try again
        reset = 1; #10; reset = 0; #10;

        // Incorrect attempts
        enter_code(4'd0, 4'd0, 4'd0, 4'd0);
        #20;
        enter_code(4'd9, 4'd9, 4'd9, 4'd9);
        #20;
        enter_code(4'd8, 4'd8, 4'd8, 4'd8);
        #50;

        $finish;
    end

endmodule

locker.vcd
$date
	Tue Jul 15 22:58:01 2025
$end
$version
	Icarus Verilog
$end
$timescale
	1ps
$end
$scope module digital_locker_tb $end
$var wire 1 ! unlocked $end
$var wire 1 " locked $end
$var wire 2 # attempts_left [1:0] $end
$var reg 1 $ clk $end
$var reg 4 % digit_in [3:0] $end
$var reg 1 & reset $end
$var reg 1 ' submit $end
$scope module uut $end
$var wire 1 $ clk $end
$var wire 4 ( digit_in [3:0] $end
$var wire 1 & reset $end
$var wire 1 ' submit $end
$var parameter 2 ) COMPARE $end
$var parameter 2 * IDLE $end
$var parameter 2 + LOCKED_STATE $end
$var parameter 2 , UNLOCKED_STATE $end
$var reg 2 - attempts_left [1:0] $end
$var reg 2 . current_state [1:0] $end
$var reg 2 / digit_index [1:0] $end
$var reg 1 " locked $end
$var reg 1 0 match_flag $end
$var reg 2 1 next_state [1:0] $end
$var reg 1 ! unlocked $end
$upscope $end
$scope task enter_code $end
$var reg 4 2 d0 [3:0] $end
$var reg 4 3 d1 [3:0] $end
$var reg 4 4 d2 [3:0] $end
$var reg 4 5 d3 [3:0] $end
$upscope $end
$upscope $end
$enddefinitions $end
$comment Show the parameter values. $end
$dumpall
b10 ,
b11 +
b0 *
b1 )
$end
#0
$dumpvars
bx 5
bx 4
bx 3
bx 2
b0 1
x0
b0 /
b0 .
b11 -
b0 (
0'
1&
b0 %
0$
b11 #
0"
0!
$end
#5000
1$
#10000
0$
#15000
1$
#20000
0$
0&
#25000
1$
#30000
0$
1'
b1 %
b1 (
b100 5
b11 4
b10 3
b1 2
#35000
b1 /
1$
#40000
0$
0'
#45000
1$
#50000
0$
1'
b10 %
b10 (
#55000
b10 /
1$
#60000
0$
0'
#65000
1$
#70000
0$
1'
b11 %
b11 (
#75000
b11 /
1$
#80000
0$
0'
#85000
1$
#90000
0$
1'
b100 %
b100 (
#95000
10
b0 /
b0 1
1$
#100000
0$
0'
#105000
1$
#110000
0$
#115000
1$
#120000
0$
#125000
1$
#130000
0$
#135000
1$
#140000
0$
#145000
1$
#150000
0$
#155000
1$
#160000
0$
1&
#165000
1$
#170000
0$
0&
#175000
1$
#180000
0$
1'
b0 %
b0 (
b0 5
b0 4
b0 3
b0 2
#185000
00
b1 /
1$
#190000
0$
0'
#195000
1$
#200000
0$
1'
#205000
b10 /
1$
#210000
0$
0'
#215000
1$
#220000
0$
1'
#225000
b11 /
1$
#230000
0$
0'
#235000
1$
#240000
0$
1'
#245000
b0 /
b0 1
1$
#250000
0$
0'
#255000
1$
#260000
0$
#265000
1$
#270000
0$
#275000
1$
#280000
0$
1'
b1001 %
b1001 (
b1001 5
b1001 4
b1001 3
b1001 2
#285000
b1 /
1$
#290000
0$
0'
#295000
1$
#300000
0$
1'
#305000
b10 /
1$
#310000
0$
0'
#315000
1$
#320000
0$
1'
#325000
b11 /
1$
#330000
0$
0'
#335000
1$
#340000
0$
1'
#345000
b0 /
b0 1
1$
#350000
0$
0'
#355000
1$
#360000
0$
#365000
1$
#370000
0$
#375000
1$
#380000
0$
1'
b1000 %
b1000 (
b1000 5
b1000 4
b1000 3
b1000 2
#385000
b1 /
1$
#390000
0$
0'
#395000
1$
#400000
0$
1'
#405000
b10 /
1$
#410000
0$
0'
#415000
1$
#420000
0$
1'
#425000
b11 /
1$
#430000
0$
0'
#435000
1$
#440000
0$
1'
#445000
b0 /
b0 1
1$
#450000
0$
0'
